kodx/__init__.py
kodx/__main__.py
kodx/cli.py
kodx/cli_ask.py
kodx/cli_code.py
kodx/cli_init.py
kodx/codex_shell.py
kodx/config.py
kodx/core.py
kodx/git_utils.py
kodx/kodx_callback.py
kodx/models.py
kodx/models_ask.py
kodx/models_code.py
kodx/prompt_utils.py
kodx/tools.py
kodx/utils.py
kodx/workspace.py
kodx/container_files/gitconfig
kodx/container_files/pty_server.py
kodx/programs/ask.yaml
kodx/programs/code.yaml
kodx/programs/default.yml
kodx-0.2.0.dist-info/METADATA
kodx-0.2.0.dist-info/WHEEL
kodx-0.2.0.dist-info/entry_points.txt
kodx-0.2.0.dist-info/licenses/LICENSE
kodx-0.2.0.dist-info/RECORD
