Metadata-Version: 2.4
Name: kodx
Version: 0.2.0
Summary: Docker-based code execution environment with LLM integration
Project-URL: repository, https://github.com/cccntu/kodx
Author: Jonathan Chang
License-Expression: Apache-2.0
License-File: LICENSE
Keywords: ai,code,docker,execution,llm
Classifier: Development Status :: 3 - Alpha
Classifier: Intended Audience :: Developers
Classifier: License :: OSI Approved :: Apache Software License
Classifier: Operating System :: OS Independent
Classifier: Programming Language :: Python :: 3
Classifier: Programming Language :: Python :: 3.11
Classifier: Programming Language :: Python :: 3.12
Requires-Python: >=3.11
Requires-Dist: click>=8.1.8
Requires-Dist: docker>=6.0.0
Requires-Dist: fastapi>=0.100.0
Requires-Dist: llmproc>=0.9.5
Requires-Dist: typer>=0.15.0
Requires-Dist: uvicorn>=0.20.0
Provides-Extra: all
Requires-Dist: anthropic>=0.52.0; extra == 'all'
Requires-Dist: google-cloud-aiplatform>=1.87.0; extra == 'all'
Requires-Dist: google-genai>=1.9.0; extra == 'all'
Requires-Dist: openai>=1.70.0; extra == 'all'
Provides-Extra: anthropic
Requires-Dist: anthropic>=0.52.0; extra == 'anthropic'
Provides-Extra: gemini
Requires-Dist: google-genai>=1.9.0; extra == 'gemini'
Provides-Extra: openai
Requires-Dist: openai>=1.70.0; extra == 'openai'
Provides-Extra: vertex
Requires-Dist: google-cloud-aiplatform>=1.87.0; extra == 'vertex'
